invoices/README.md
invoices/__init__.py
invoices/admin.py
invoices/api.py
invoices/app_settings.py
invoices/apps.py
invoices/auth_hooks.py
invoices/cogs.py
invoices/managers.py
invoices/models.py
invoices/schema.py
invoices/tasks.py
invoices/urls.py
invoices/views.py
invoices/locale/en/LC_MESSAGES/django.po
invoices/management/__init__.py
invoices/management/commands/__init__.py
invoices/management/commands/process_from_characters.py
invoices/migrations/0001_initial.py
invoices/migrations/0002_auto_20201008_0937.py
invoices/migrations/0003_invoice_note.py
invoices/migrations/0004_auto_20201012_0303.py
invoices/migrations/0005_auto_20201013_0310.py
invoices/migrations/0006_nooverduefilter.py
invoices/migrations/0007_nooverduefilter_swap_logic.py
invoices/migrations/0008_totalinvoicesfilter.py
invoices/migrations/0009_invoice_marked_paid_by.py
invoices/migrations/0010_alter_invoice_marked_paid_by.py
invoices/migrations/__init__.py
invoices/static/css/invoices-style.css
invoices/static/invoices/manifest.json
invoices/static/invoices/assets/@libs-Dqtl1Gnx.js
invoices/static/invoices/assets/@libs-Dqtl1Gnx.js.map
invoices/static/invoices/assets/index-Bk5Uhpr3.js
invoices/static/invoices/assets/index-Bk5Uhpr3.js.map
invoices/static/invoices/static/css/index-DGGPf4Q8.css
invoices/static/invoices/static/static/css/index-DGGPf4Q8.css
invoices/templates/invoices/admin.html
invoices/templates/invoices/list.html
invoices/templates/invoices/react_base.html
invoices/templates/invoices/react_base_bs5.html
invoices/templatetags/__init__.py
invoices/templatetags/invoices.py
invoices/tests/__init__.py
invoices/tests/test_access.py
invoices/tests/test_filter.py
allianceauth_invoices-0.1.8.dist-info/licenses/LICENSE
allianceauth_invoices-0.1.8.dist-info/WHEEL
allianceauth_invoices-0.1.8.dist-info/METADATA
allianceauth_invoices-0.1.8.dist-info/RECORD
