Metadata-Version: 2.4
Name: allianceauth-invoices
Version: 0.1.8
Summary: Invoice module for AllianceAuth with simplicity and extendability in mind.
Keywords: allianceauth,eveonline
Author-email: AaronKable <aaronkable@gmail.com>
Requires-Python: >=3.8
Classifier: Environment :: Web Environment
Classifier: Framework :: Celery
Classifier: Framework :: Django
Classifier: Framework :: Django :: 4.0
Classifier: Framework :: Django :: 4.2
Classifier: Intended Audience :: Developers
Classifier: License :: OSI Approved :: MIT License
Classifier: Operating System :: OS Independent
Classifier: Programming Language :: Python
Classifier: Programming Language :: Python :: 3 :: Only
Classifier: Programming Language :: Python :: 3.8
Classifier: Programming Language :: Python :: 3.9
Classifier: Programming Language :: Python :: 3.10
Classifier: Programming Language :: Python :: 3.11
Classifier: Programming Language :: Python :: 3.12
Classifier: Programming Language :: Python :: Implementation :: CPython
Classifier: Topic :: Internet :: WWW/HTTP
Classifier: Topic :: Internet :: WWW/HTTP :: Dynamic Content
License-File: LICENSE
Requires-Dist: allianceauth>=3,<5
Requires-Dist: allianceauth-corptools>=2.5.5
Project-URL: Home, https://github.com/Solar-Helix-Independent-Transport/allianceauth-invoice-manager
Project-URL: Source, https://github.com/Solar-Helix-Independent-Transport/allianceauth-invoice-manager
Project-URL: Tracker, https://github.com/Solar-Helix-Independent-Transport/allianceauth-invoice-manager/issues
